setup.py
giturlparse/__init__.py
giturlparse/parser.py
giturlparse/result.py
giturlparse.py.egg-info/PKG-INFO
giturlparse.py.egg-info/SOURCES.txt
giturlparse.py.egg-info/dependency_links.txt
giturlparse.py.egg-info/top_level.txt
giturlparse/platforms/__init__.py
giturlparse/platforms/assembla.py
giturlparse/platforms/base.py
giturlparse/platforms/bitbucket.py
giturlparse/platforms/friendcode.py
giturlparse/platforms/github.py