Metadata-Version: 1.0
Name: giturlparse.py
Version: 0.0.2
Summary: A Git URL parsing module (supports parsing and rewriting)
Home-page: https://github.com/FriendCode/giturlparse.py
Author: Aaron O'Mullan
Author-email: aaron@friendco.de
License: Apache v2
Keywords: git url parse ssh github bitbucket
Platform: UNKNOWN
